[
    {
        "transactionName": "Patient operations_ Get2DCodeImage",
        "rawStartTime": 1525250641815,
        "rawEndTime": 1525250642374
    },
    {
        "transactionName": "GetPatientQRID",
        "rawStartTime": 1525250643402,
        "rawEndTime": 1525250643703
    },
    {
        "transactionName": "Patient Subscribe_Patinet",
        "rawStartTime": 1525250644740,
        "rawEndTime": 1525250645051
    },
    {
        "transactionName": "Film Create Film",
        "rawStartTime": 1525250645097,
        "rawEndTime": 1525250646154
    },
    {
        "transactionName": "Film QueryReportFilmStatus",
        "rawStartTime": 1525250647167,
        "rawEndTime": 1525250647469
    },
    {
        "transactionName": "Film Update Film",
        "rawStartTime": 1525250648482,
        "rawEndTime": 1525250649471
    },
    {
        "transactionName": "Film QueryReportFilmStatus",
        "rawStartTime": 1525250650486,
        "rawEndTime": 1525250650794
    }
]